circles/__init__.py
circles/__main__.py
circles/cv_helper.py
circles/exceptions.py
circles/interpreter.py
circles/main.py
circles/parser.py
circles/program.py
circleso-0.1.0.dist-info/WHEEL
circleso-0.1.0.dist-info/METADATA
circleso-0.1.0.dist-info/RECORD
